regolith_system_template/__init__.py
regolith_system_template/merge.py
regolith_system_template/py.typed
regolith_system_template-1.4.0.dist-info/licenses/LICENSE
regolith_system_template-1.4.0.dist-info/METADATA
regolith_system_template-1.4.0.dist-info/WHEEL
regolith_system_template-1.4.0.dist-info/entry_points.txt
regolith_system_template-1.4.0.dist-info/top_level.txt
regolith_system_template-1.4.0.dist-info/RECORD
