Metadata-Version: 2.4
Name: regolith-system-template
Version: 1.4.0
Summary: A Python package for easier reuseability of the System Template Regolith filter for Minecraft Bedrock Edition
Author: Nusiq
License: MIT
Project-URL: Source, https://github.com/Nusiq/regolith-system-template/tree/master
Classifier: Development Status :: 5 - Production/Stable
Classifier: License :: OSI Approved :: MIT License
Classifier: Programming Language :: Python :: 3.11
Requires-Python: >=3.10
License-File: LICENSE
Requires-Dist: better-json-tools~=1.0.3
Requires-Dist: regolith-subfunctions~=1.4.0
Requires-Dist: regolith-json-template~=1.3.1
Dynamic: license-file
